pytest_lineno/__init__.py
pytest_lineno-0.0.1.dist-info/LICENSE
pytest_lineno-0.0.1.dist-info/METADATA
pytest_lineno-0.0.1.dist-info/WHEEL
pytest_lineno-0.0.1.dist-info/entry_points.txt
pytest_lineno-0.0.1.dist-info/top_level.txt
pytest_lineno-0.0.1.dist-info/RECORD
