Metadata-Version: 2.1
Name: pytest-lineno
Version: 0.0.1
Summary: A pytest plugin to show the line numbers of test functions
Home-page: UNKNOWN
Author: harupy
License: MIT
Platform: UNKNOWN
Requires-Python: >=3.5
Requires-Dist: pytest
Provides-Extra: dev
Requires-Dist: black ; extra == 'dev'
Requires-Dist: flake8 ; extra == 'dev'
Requires-Dist: wheel ; extra == 'dev'
